README.md
setup.py
antimait/__init__.py
antimait/plotting.py
antimait.egg-info/PKG-INFO
antimait.egg-info/SOURCES.txt
antimait.egg-info/dependency_links.txt
antimait.egg-info/requires.txt
antimait.egg-info/top_level.txt
scripts/antimait_printer